{ 
    "module": {
        "name": "Zepi Core Access Control",
        "description": "This module controls the access to the routes. Every object (i.e. user, group, api key) has a UUID and the access is granted to the UUID.",
        "namespace": "\\Zepi\\Core\\AccessControl",
        "author": "Matthias Zobrist",
        "copyright": "(C) Copyright 2014 by Matthias Zobrist",
        "url": "http://www.zepi.net/",
        "version": "1.0"
    },
    "dependencies": {
        "required": {
            "\\Zepi\\Core\\Utils": "*",
            "\\Zepi\\DataSourceDriver\\Doctrine": "*"
        }
    }
}
